xyz_warehouse/__init__.py
xyz_warehouse/admin.py
xyz_warehouse/apis.py
xyz_warehouse/apps.py
xyz_warehouse/choices.py
xyz_warehouse/cron.py
xyz_warehouse/helper.py
xyz_warehouse/mixins.py
xyz_warehouse/models.py
xyz_warehouse/nodes.py
xyz_warehouse/receivers.py
xyz_warehouse/serializers.py
xyz_warehouse/stat.py
xyz_warehouse/tasks.py
xyz_warehouse-0.1.0.dist-info/METADATA
xyz_warehouse-0.1.0.dist-info/WHEEL
xyz_warehouse-0.1.0.dist-info/top_level.txt
xyz_warehouse-0.1.0.dist-info/RECORD
